akv_tui/__init__.py
akv_tui/_version.py
akv_tui/app.py
akv_tui/helpers.py
akv_tui/services.py
akv_tui-0.1.1.dist-info/METADATA
akv_tui-0.1.1.dist-info/WHEEL
akv_tui-0.1.1.dist-info/entry_points.txt
akv_tui-0.1.1.dist-info/licenses/LICENSE
akv_tui-0.1.1.dist-info/RECORD
