Metadata-Version: 2.4
Name: akv-tui
Version: 0.1.1
Summary: Simple TUI to search Azure KeyVault
Author-email: Jonathan Kößler <mail@jonathan-koessler.de>
License: MIT License
License-File: LICENSE
Classifier: Development Status :: 4 - Beta
Classifier: Intended Audience :: Developers
Classifier: License :: OSI Approved :: MIT License
Classifier: Operating System :: OS Independent
Classifier: Programming Language :: Python
Classifier: Programming Language :: Python :: 3.11
Classifier: Programming Language :: Python :: 3.12
Classifier: Programming Language :: Python :: 3.13
Requires-Python: <3.14,>=3.11
Requires-Dist: azure-identity>=1.23.0
Requires-Dist: azure-keyvault>=4.2.0
Requires-Dist: azure-mgmt-keyvault>=11.0.0
Requires-Dist: azure-mgmt-resource>=24.0.0
Requires-Dist: pyperclip>=1.9.0
Requires-Dist: textual>=3.4.0
